denormalize/__init__.py
denormalize-0.0.3.dist-info/METADATA
denormalize-0.0.3.dist-info/WHEEL
denormalize-0.0.3.dist-info/licenses/LICENSE
denormalize-0.0.3.dist-info/RECORD
