Metadata-Version: 2.1
Name: denormalize
Version: 0.0.3
Summary: A single-cell denormalization tool
Author-email: Lirong Yang <lirong.yang@outlook.com>
License-File: LICENSE
Classifier: License :: OSI Approved :: MIT License
Classifier: Operating System :: OS Independent
Classifier: Programming Language :: Python :: 3
Requires-Python: >=3.7
